{
  "interactionModel": {
    "languageModel": {
      "invocationName": "take me somewhere",
      "intents": [{
          "name": "AMAZON.CancelIntent",
          "samples": [

          ]
        },
        {
          "name": "AMAZON.HelpIntent",
          "samples": [

          ]
        },
        {
          "name": "AMAZON.StopIntent",
          "samples": [

          ]
        },
        {
          "name": "FindLocationIntent",
          "slots": [{
              "name": "weather",
              "type": "AMAZON.WeatherCondition"
            },
            {
              "name": "country",
              "type": "AMAZON.Country"
            }
          ],
          "samples": [
            "{country}",
            "{weather}",
            "I like it {weather}",
            "I like {weather} weather",
            "i want to visit {country}",
            "Where it is {weather}"
          ]
        },
        {
          "name": "MoveIntent",
          "samples": [
            "go {direction}",
            "move {direction}",
            "slightly {direction}",
            "{direction}"
          ],
          "slots": [{
            "name": "direction",
            "type": "LIST_OF_DIRECTIONS"
          }]
        },
        {
          "name": "ZoomIntent",
          "samples": [
            "zoom {zoom}",
            "zoom {zoom}",
            "make it {zoom}",
            "make it {zoom}"
          ],
          "slots": [{
            "name": "zoom",
            "type": "LIST_OF_ZOOM_LEVELS"
          }]
        },
        {
          "name": "MapTypeIntent",
          "samples": [
            "Can you show me the {map} map",
            "Display {map} map",
            "I would like to see {map} map",
            "I would rather see {map} map"
          ],
          "slots": [{
            "name": "map",
            "type": "LIST_OF_MAP_TYPES"
          }]
        },
        {
          "name": "VRIntent",
          "samples": [
            "I would like to see this in VR",
            "Can you show me this in VR",
            "Open VR mode",
            "Show me in VR",
            "Go into VR mode"
          ],
          "slots": []
        },
        {
          "name": "PitchIntent",
          "samples": [
            "Help me with the pitch"
          ],
          "slots": []
        }
      ],
      "types": [{
          "name": "LIST_OF_DIRECTIONS",
          "values": [{
            "name": {
              "value": "north",
              "synonyms": ["up"]
            }
          }, {
            "name": {
              "value": "south",
              "synonyms": ["down"]
            }
          }, {
            "name": {
              "value": "east",
              "synonyms": ["right"]
            }
          }, {
            "name": {
              "value": "west",
              "synonyms": ["left"]
            }
          }]
        },
        {
          "name": "LIST_OF_ZOOM_LEVELS",
          "values": [{
              "name": {
                "value": "in",
                "synonyms": ["bigger"]
              }
            },
            {
              "name": {
                "value": "out",
                "synonyms": ["smaller"]
              }
            }
          ]
        },
        {
          "name": "LIST_OF_MAP_TYPES",
          "values": [{
              "name": {
                "value": "default",
                "synonyms": ["natural"]
              }
            },
            {
              "name": {
                "value": "agriculture",
                "synonyms": []
              }
            },
            {
              "name": {
                "value": "vegetation",
                "synonyms": []
              }
            },
            {
              "name": {
                "value": "urban",
                "synonyms": []
              }
            },
            {
              "name": {
                "value": "moisture",
                "synonyms": []
              }
            }
          ]
        }
      ]
    }
  }
}
